{
    "marbles": {
        "MartianMoocat": [
            {
                "position": 1,
                "individual": 100,
                "total": 100
            }
        ],
        "superbcount": [
            {
                "position": 2,
                "individual": 99,
                "total": 99
            }
        ],
        "wehooper4": [
            {
                "position": 3,
                "individual": 98,
                "total": 98
            }
        ],
        "KelsConditional": [
            {
                "position": 4,
                "individual": 97,
                "total": 97
            }
        ],
        "sorasfishing": [
            {
                "position": 5,
                "individual": 96,
                "total": 96
            }
        ],
        "yourownmomv2": [
            {
                "position": 6,
                "individual": 95,
                "total": 95
            }
        ],
        "Socially_Odd260": [
            {
                "position": 7,
                "individual": 94,
                "total": 94
            }
        ],
        "Jason_Worthing": [
            {
                "position": 8,
                "individual": 93,
                "total": 93
            }
        ],
        "Saintsrow123474": [
            {
                "position": 9,
                "individual": 92,
                "total": 92
            }
        ],
        "Atiggerx33": [
            {
                "position": 10,
                "individual": 91,
                "total": 91
            }
        ],
        "Sneakiest": [
            {
                "position": 11,
                "individual": 90,
                "total": 90
            }
        ],
        "jharish": [
            {
                "position": 12,
                "individual": 89,
                "total": 89
            }
        ],
        "Clint28": [
            {
                "position": 13,
                "individual": 88,
                "total": 88
            }
        ],
        "mongrol-sludge": [
            {
                "position": 14,
                "individual": 87,
                "total": 87
            }
        ],
        "jumbledzebra": [
            {
                "position": 15,
                "individual": 86,
                "total": 86
            }
        ],
        "PlasmaStark": [
            {
                "position": 16,
                "individual": 85,
                "total": 85
            }
        ],
        "Timo6506": [
            {
                "position": 17,
                "individual": 84,
                "total": 84
            }
        ],
        "sritik617": [
            {
                "position": 18,
                "individual": 83,
                "total": 83
            }
        ],
        "Cit_63": [
            {
                "position": 19,
                "individual": 82,
                "total": 82
            }
        ],
        "simcoecitra": [
            {
                "position": 20,
                "individual": 81,
                "total": 81
            }
        ],
        "VibrantVioletGrace": [
            {
                "position": 21,
                "individual": 80,
                "total": 80
            }
        ],
        "Elfishjuggler33": [
            {
                "position": 22,
                "individual": 79,
                "total": 79
            }
        ],
        "Mindris": [
            {
                "position": 23,
                "individual": 78,
                "total": 78
            }
        ],
        "Magnus-Artifex": [
            {
                "position": 24,
                "individual": 77,
                "total": 77
            }
        ],
        "Dizzzyyyy": [
            {
                "position": 25,
                "individual": 76,
                "total": 76
            }
        ],
        "Annoelle": [
            {
                "position": 26,
                "individual": 75,
                "total": 75
            }
        ],
        "I_no_verylittle": [
            {
                "position": 27,
                "individual": 74,
                "total": 74
            }
        ],
        "Mr_Wafflz": [
            {
                "position": 28,
                "individual": 73,
                "total": 73
            }
        ],
        "EngineeringMySadness": [
            {
                "position": 29,
                "individual": 72,
                "total": 72
            }
        ],
        "the_dh_junkie": [
            {
                "position": 30,
                "individual": 71,
                "total": 71
            }
        ],
        "OrangeSockMonkey": [
            {
                "position": 31,
                "individual": 70,
                "total": 70
            }
        ],
        "MoscaMye": [
            {
                "position": 32,
                "individual": 69,
                "total": 69
            }
        ],
        "T-R-W": [
            {
                "position": 33,
                "individual": 68,
                "total": 68
            }
        ],
        "Naima22": [
            {
                "position": 34,
                "individual": 67,
                "total": 67
            }
        ],
        "TK_Sleepytime": [
            {
                "position": 35,
                "individual": 66,
                "total": 66
            }
        ],
        "insolent_swine": [
            {
                "position": 36,
                "individual": 65,
                "total": 65
            }
        ],
        "AvgMick": [
            {
                "position": 37,
                "individual": 64,
                "total": 64
            }
        ],
        "sargon76": [
            {
                "position": 38,
                "individual": 63,
                "total": 63
            }
        ],
        "Fluffybagel": [
            {
                "position": 39,
                "individual": 62,
                "total": 62
            }
        ],
        "instit0r": [
            {
                "position": 40,
                "individual": 61,
                "total": 61
            }
        ],
        "_wwwdotcreedthoughts": [
            {
                "position": 41,
                "individual": 60,
                "total": 60
            }
        ],
        "Kanexan": [
            {
                "position": 42,
                "individual": 59,
                "total": 59
            }
        ],
        "DogMechanic": [
            {
                "position": 43,
                "individual": 58,
                "total": 58
            }
        ],
        "Ethrem": [
            {
                "position": 44,
                "individual": 57,
                "total": 57
            }
        ],
        "kupaa": [
            {
                "position": 45,
                "individual": 56,
                "total": 56
            }
        ],
        "moskayjoh": [
            {
                "position": 46,
                "individual": 55,
                "total": 55
            }
        ],
        "SkullDaisyGimp": [
            {
                "position": 47,
                "individual": 54,
                "total": 54
            }
        ],
        "Herald_Osbert": [
            {
                "position": 48,
                "individual": 53,
                "total": 53
            }
        ],
        "Aurallius": [
            {
                "position": 49,
                "individual": 52,
                "total": 52
            }
        ],
        "MidnightJ1200": [
            {
                "position": 50,
                "individual": 51,
                "total": 51
            }
        ],
        "KreiaIncarnate": [
            {
                "position": 51,
                "individual": 50,
                "total": 50
            }
        ],
        "notyourusualsaturday": [
            {
                "position": 52,
                "individual": 49,
                "total": 49
            }
        ],
        "IShotAGrapefruit7": [
            {
                "position": 53,
                "individual": 48,
                "total": 48
            }
        ],
        "hackersbevy": [
            {
                "position": 54,
                "individual": 47,
                "total": 47
            }
        ],
        "BandicootSecure": [
            {
                "position": 55,
                "individual": 46,
                "total": 46
            }
        ],
        "Cobaltbuzzsaw7": [
            {
                "position": 56,
                "individual": 45,
                "total": 45
            }
        ],
        "VincentJoshuaET": [
            {
                "position": 57,
                "individual": 44,
                "total": 44
            }
        ],
        "Pessimist2020": [
            {
                "position": 58,
                "individual": 43,
                "total": 43
            }
        ],
        "Jay2612": [
            {
                "position": 59,
                "individual": 42,
                "total": 42
            }
        ],
        "CheepCheepChompYT": [
            {
                "position": 60,
                "individual": 41,
                "total": 41
            }
        ],
        "Roomination": [
            {
                "position": 61,
                "individual": 40,
                "total": 40
            }
        ],
        "jiggle-o": [
            {
                "position": 62,
                "individual": 39,
                "total": 39
            }
        ],
        "yankeebelles": [
            {
                "position": 63,
                "individual": 38,
                "total": 38
            }
        ],
        "Sir_Poofs_Alot": [
            {
                "position": 64,
                "individual": 37,
                "total": 37
            }
        ],
        "Pzwang4": [
            {
                "position": 65,
                "individual": 36,
                "total": 36
            }
        ],
        "luri7555": [
            {
                "position": 66,
                "individual": 35,
                "total": 35
            }
        ],
        "Aldroe": [
            {
                "position": 67,
                "individual": 34,
                "total": 34
            }
        ],
        "TheMelonOwl": [
            {
                "position": 68,
                "individual": 33,
                "total": 33
            }
        ],
        "MisterVaridoianis": [
            {
                "position": 69,
                "individual": 32,
                "total": 32
            }
        ],
        "s1gnalZer0": [
            {
                "position": 70,
                "individual": 31,
                "total": 31
            }
        ],
        "deadwlkn": [
            {
                "position": 71,
                "individual": 30,
                "total": 30
            }
        ],
        "background_spider": [
            {
                "position": 72,
                "individual": 29,
                "total": 29
            }
        ],
        "PrismRanger": [
            {
                "position": 73,
                "individual": 28,
                "total": 28
            }
        ],
        "Vanilla_Princess": [
            {
                "position": 74,
                "individual": 27,
                "total": 27
            }
        ],
        "Wormcoil": [
            {
                "position": 75,
                "individual": 26,
                "total": 26
            }
        ],
        "H2Joee": [
            {
                "position": 76,
                "individual": 25,
                "total": 25
            }
        ],
        "Fuck_Shinji": [
            {
                "position": 77,
                "individual": 24,
                "total": 24
            }
        ],
        "moosepile": [
            {
                "position": 78,
                "individual": 23,
                "total": 23
            }
        ],
        "njones1220": [
            {
                "position": 79,
                "individual": 22,
                "total": 22
            }
        ],
        "weeghostie00": [
            {
                "position": 80,
                "individual": 21,
                "total": 21
            }
        ],
        "Terrh": [
            {
                "position": 81,
                "individual": 20,
                "total": 20
            }
        ],
        "thefifthangel141": [
            {
                "position": 82,
                "individual": 19,
                "total": 19
            }
        ],
        "PM_ME_YOUR_STOCKPIX": [
            {
                "position": 83,
                "individual": 18,
                "total": 18
            }
        ],
        "InspirobotBot": [
            {
                "position": 84,
                "individual": 17,
                "total": 17
            }
        ],
        "zirky": [
            {
                "position": 85,
                "individual": 16,
                "total": 16
            }
        ],
        "Archy99": [
            {
                "position": 86,
                "individual": 15,
                "total": 15
            }
        ],
        "Zokalyx": [
            {
                "position": 87,
                "individual": 14,
                "total": 14
            }
        ],
        "a_coward_irl": [
            {
                "position": 88,
                "individual": 13,
                "total": 13
            }
        ],
        "jef__fay": [
            {
                "position": 89,
                "individual": 12,
                "total": 12
            }
        ],
        "surfaholic15": [
            {
                "position": 90,
                "individual": 11,
                "total": 11
            }
        ],
        "write-csv": [
            {
                "position": 91,
                "individual": 10,
                "total": 10
            }
        ],
        "Man-akle": [
            {
                "position": 92,
                "individual": 9,
                "total": 9
            }
        ],
        "cniinc": [
            {
                "position": 93,
                "individual": 8,
                "total": 8
            }
        ],
        "Almighty_Elephant": [
            {
                "position": 94,
                "individual": 7,
                "total": 7
            }
        ],
        "yo-whatupmofo": [
            {
                "position": 95,
                "individual": 6,
                "total": 6
            }
        ],
        "IAmTheClayman": [
            {
                "position": 96,
                "individual": 5,
                "total": 5
            }
        ],
        "Thejusko": [
            {
                "position": 97,
                "individual": 4,
                "total": 4
            }
        ],
        "hairysonorth": [
            {
                "position": 98,
                "individual": 3,
                "total": 3
            }
        ],
        "CommaDelimitedList": [
            {
                "position": 99,
                "individual": 2,
                "total": 2
            }
        ],
        "dede-javu": [
            {
                "position": 100,
                "individual": 1,
                "total": 1
            }
        ],
        "kregerator": [
            {
                "position": 101,
                "individual": 0,
                "total": 0
            }
        ],
        "Connir": [
            {
                "position": 102,
                "individual": 0,
                "total": 0
            }
        ],
        "8Legs-2Tentacles": [
            {
                "position": 103,
                "individual": 0,
                "total": 0
            }
        ],
        "sharkbaiting10": [
            {
                "position": 104,
                "individual": 0,
                "total": 0
            }
        ],
        "CrixusDaGaul": [
            {
                "position": 105,
                "individual": 0,
                "total": 0
            }
        ],
        "roadkillchef_1": [
            {
                "position": 106,
                "individual": 0,
                "total": 0
            }
        ],
        "pl233": [
            {
                "position": 107,
                "individual": 0,
                "total": 0
            }
        ],
        "mafaldinha": [
            {
                "position": 108,
                "individual": 0,
                "total": 0
            }
        ],
        "Netherpizza": [
            {
                "position": 109,
                "individual": 0,
                "total": 0
            }
        ],
        "UntouchedSack": [
            {
                "position": 110,
                "individual": 0,
                "total": 0
            }
        ],
        "FrozenExpanse": [
            {
                "position": 111,
                "individual": 0,
                "total": 0
            }
        ],
        "ZackTheSmack": [
            {
                "position": 112,
                "individual": 0,
                "total": 0
            }
        ],
        "fireamoe": [
            {
                "position": 113,
                "individual": 0,
                "total": 0
            }
        ],
        "saraena": [
            {
                "position": 114,
                "individual": 0,
                "total": 0
            }
        ],
        "datanas": [
            {
                "position": 115,
                "individual": 0,
                "total": 0
            }
        ],
        "MyNewAlt5836484": [
            {
                "position": 116,
                "individual": 0,
                "total": 0
            }
        ],
        "goomba456": [
            {
                "position": 117,
                "individual": 0,
                "total": 0
            }
        ],
        "AlocasterTV": [
            {
                "position": 118,
                "individual": 0,
                "total": 0
            }
        ],
        "nopage": [
            {
                "position": 119,
                "individual": 0,
                "total": 0
            }
        ],
        "Pharmacodynamical": [
            {
                "position": 120,
                "individual": 0,
                "total": 0
            }
        ],
        "Deusyl": [
            {
                "position": 121,
                "individual": 0,
                "total": 0
            }
        ],
        "boardatwork1111": [
            {
                "position": 122,
                "individual": 0,
                "total": 0
            }
        ],
        "nimbleseaurchin": [
            {
                "position": 123,
                "individual": 0,
                "total": 0
            }
        ],
        "tundrawolf89": [
            {
                "position": 124,
                "individual": 0,
                "total": 0
            }
        ],
        "highrelevance": [
            {
                "position": 125,
                "individual": 0,
                "total": 0
            }
        ],
        "Forretressqt": [
            {
                "position": 126,
                "individual": 0,
                "total": 0
            }
        ],
        "JebSenrab": [
            {
                "position": 127,
                "individual": 0,
                "total": 0
            }
        ]
    },
    "dnf-marbles": [
        0
    ]
}